[
  {
    "Tracking": "CD09_001",
    "CodLocalidadOrigen": "CABA",
    "CodCentroDistribucionOrigen": "CD01",
    "CodCentroDistribucionDestino": "CD09",
    "Estado": 12,
    "TipoBulto": 1,
    "CUITCliente": "30-19283746-40",
    "DNIDestinatario": 35678901,
    "NombreDestinatario": "Lucía",
    "ApellidoDestinatario": "Ramírez",
    "DireccionDestinatario": null,
    "AgenciaOrigen": null,
    "AgenciaDestino": null,
    "DatosRetiroADomicilio": "Calle Falsa 123, Piso 4, CABA",
    "CodCDActual": "CD09",
    "ParadasRuta": [ 1, 5, 9 ],
    "FechaImposicion": "2025-10-03T09:30:00",
    "FechaAdmision": "2025-10-04T12:45:00",
    "FechaEntrega": "2025-10-06T16:20:00",
    "EncomiendaFactura": {
      "PrecioCombinacionTamanoOrigenDestino": 1300,
      "ExtraRetiro": 1750,
      "ExtraAgencia": 0,
      "ExtraEntrega": 0,
      "PrecioTotalEncomienda": 3050
    },
    "HistorialCambios": [
      {
        "Tracking": "CD09_001",
        "FechaPrevia": "2025-10-03T09:30:00",
        "UbicacionPrevia": null,
        "FleteroAsignado": 0,
        "NumeroHDRUM": 0,
        "NumeroHDRMD": 0,
        "EstadoPrevio": 0
      },
      {
        "Tracking": "CD09_001",
        "FechaPrevia": "2025-10-03T10:00:00",
        "UbicacionPrevia": null,
        "FleteroAsignado": 12345678,
        "NumeroHDRUM": 1101,
        "NumeroHDRMD": 0,
        "EstadoPrevio": 2
      },
      {
        "Tracking": "CD09_001",
        "FechaPrevia": "2025-10-04T08:15:00",
        "UbicacionPrevia": "CD01",
        "FleteroAsignado": 12345678,
        "NumeroHDRUM": 1101,
        "NumeroHDRMD": 2001,
        "EstadoPrevio": 4
      },
      {
        "Tracking": "CD09_001",
        "FechaPrevia": "2025-10-04T12:45:00",
        "UbicacionPrevia": "CD01",
        "FleteroAsignado": 12345678,
        "NumeroHDRUM": 0,
        "NumeroHDRMD": 2001,
        "EstadoPrevio": 5
      },
      {
        "Tracking": "CD09_001",
        "FechaPrevia": "2025-10-05T22:00:00",
        "UbicacionPrevia": "CD09",
        "FleteroAsignado": 0,
        "NumeroHDRUM": 0,
        "NumeroHDRMD": 2001,
        "EstadoPrevio": 6
      },
      {
        "Tracking": "CD09_001",
        "FechaPrevia": "2025-10-06T10:00:00",
        "UbicacionPrevia": "CD09",
        "FleteroAsignado": 0,
        "NumeroHDRUM": 0,
        "NumeroHDRMD": 2001,
        "EstadoPrevio": 7
      }
    ],
    "Facturada": false
  },
  {
    "Tracking": "CD09_002",
    "CodLocalidadOrigen": "CorC",
    "CodCentroDistribucionOrigen": "CD05",
    "CodCentroDistribucionDestino": "CD09",
    "Estado": 7,
    "TipoBulto": 2,
    "CUITCliente": "27-38951233-5",
    "DNIDestinatario": 40875690,
    "NombreDestinatario": "Marcos",
    "ApellidoDestinatario": "Fernández",
    "DireccionDestinatario": null,
    "AgenciaOrigen": null,
    "AgenciaDestino": null,
    "DatosRetiroADomicilio": null,
    "CodCDActual": "CD05",
    "ParadasRuta": [ 301, 302 ],
    "FechaImposicion": "2025-11-27T09:45:00",
    "FechaAdmision": "2025-11-27T09:45:00",
    "FechaEntrega": null,
    "EncomiendaFactura": {
      "PrecioCombinacionTamanoOrigenDestino": 1870,
      "ExtraRetiro": 0,
      "ExtraAgencia": 0,
      "ExtraEntrega": 0,
      "PrecioTotalEncomienda": 1870
    },
    "HistorialCambios": [
      {
        "Tracking": "CD09_002",
        "FechaPrevia": "2025-11-27T09:30:00",
        "UbicacionPrevia": "CD05",
        "FleteroAsignado": 0,
        "NumeroHDRUM": 0,
        "NumeroHDRMD": 2005,
        "EstadoPrevio": 5
      }
    ],
    "Facturada": false
   
  },
  {
    "Tracking": "CD11_001",
    "CodLocalidadOrigen": "CC",
    "CodCentroDistribucionOrigen": "CD09",
    "CodCentroDistribucionDestino": "CD11",
    "Estado": 5,
    "TipoBulto": 1,
    "CUITCliente": "30-87651234-0",
    "DNIDestinatario": 39456780,
    "NombreDestinatario": "Camila",
    "ApellidoDestinatario": "Roldán",
    "DireccionDestinatario": null,
    "AgenciaOrigen": null,
    "AgenciaDestino": null,
    "DatosRetiroADomicilio": null,
    "CodCDActual": "CD09",
    "ParadasRuta": [ 302, 201 ],
    "FechaImposicion": "2025-11-28T17:00:00",
    "FechaAdmision": "2025-11-28T18:15:00",
    "FechaEntrega": null,
    "EncomiendaFactura": {
      "PrecioCombinacionTamanoOrigenDestino": 1820,
      "ExtraRetiro": 0,
      "ExtraAgencia": 0,
      "ExtraEntrega": 0,
      "PrecioTotalEncomienda": 1820
    },

    "HistorialCambios": [],
    "Facturada": false
  },

  {
    "Tracking": "AG04_001",
    "CodLocalidadOrigen": "CorC",
    "CodCentroDistribucionOrigen": "CD05",
    "CodCentroDistribucionDestino": "CD02",
    "Estado": 11,
    "TipoBulto": 1,
    "CUITCliente": "30-87651234-00",
    "DNIDestinatario": 39567890,
    "NombreDestinatario": "Julieta",
    "ApellidoDestinatario": "Soria",
    "DireccionDestinatario": null,
    "AgenciaOrigen": null,
    "AgenciaDestino": "Agencia Belgrano",
    "DatosRetiroADomicilio": null,
    "CodCDActual": "CD02",
    "ParadasRuta": [ 205, 210 ],
    "FechaImposicion": "2025-11-20T09:30:00",
    "FechaAdmision": "2025-11-20T10:00:00",
    "FechaEntrega": null,
    "EncomiendaFactura": {
      "PrecioCombinacionTamanoOrigenDestino": 1600,
      "ExtraRetiro": 0,
      "ExtraAgencia": 1200,
      "ExtraEntrega": 0,
      "PrecioTotalEncomienda": 2800
    },
    "HistorialCambios": [
      {
        "Tracking": "AG04_001",
        "FechaPrevia": "2025-11-20T09:30:00",
        "UbicacionPrevia": "CD05",
        "FleteroAsignado": 0,
        "NumeroHDRUM": 0,
        "NumeroHDRMD": 2010,
        "EstadoPrevio": 10
      }
    ],
    "Facturada": false
  },
  {
    "Tracking": "CD05_010",
    "CodLocalidadOrigen": "CABA",
    "CodCentroDistribucionOrigen": "CD01",
    "CodCentroDistribucionDestino": "CD05",
    "Estado": 7,
    "TipoBulto": 2,
    "CUITCliente": "30-19283746-4",
    "DNIDestinatario": 40894321,
    "NombreDestinatario": "Ignacio",
    "ApellidoDestinatario": "Romero",
    "DireccionDestinatario": null,
    "AgenciaOrigen": "Agencia Abasto",
    "AgenciaDestino": null,
    "DatosRetiroADomicilio": null,
    "CodCDActual": "CD05",
    "ParadasRuta": [ 301, 302 ],
    "FechaImposicion": "2025-11-22T10:30:00",
    "FechaAdmision": "2025-11-22T11:00:00",
    "FechaEntrega": null,
    "EncomiendaFactura": {
      "PrecioCombinacionTamanoOrigenDestino": 1700,
      "ExtraRetiro": 0,
      "ExtraAgencia": 0,
      "ExtraEntrega": 0,
      "PrecioTotalEncomienda": 1700
    },
    "HistorialCambios": [
      {
        "Tracking": "CD05_010",
        "FechaPrevia": "2025-11-22T10:30:00",
        "UbicacionPrevia": "Agencia Abasto",
        "FleteroAsignado": 0,
        "NumeroHDRUM": 0,
        "NumeroHDRMD": 2011,
        "EstadoPrevio": 6
      }
    ],
    "Facturada": false
  }


]